tests/__init__.py
uniqcharstest8-1.0.dist-info/LICENSE
uniqcharstest8-1.0.dist-info/METADATA
uniqcharstest8-1.0.dist-info/WHEEL
uniqcharstest8-1.0.dist-info/entry_points.txt
uniqcharstest8-1.0.dist-info/top_level.txt
uniqcharstest8-1.0.dist-info/RECORD
